{
  "candidate_count": 288,
  "comparison_status": "SAME_AS_PREVIOUS",
  "comparison_tolerance": 1e-09,
  "completed_count": 288,
  "current_hardest": {
    "candidate_index": 191,
    "chain_episodes": 18,
    "hardest_episode": {
      "chain_average_debt": 1.4285714285714286,
      "chain_blocks": 7,
      "chain_debt": 10,
      "chain_deficit_below_threshold": 0.15639107214972747,
      "chain_end_block": 143,
      "chain_end_event_index": 31,
      "chain_length_segments": 1,
      "chain_max_cheapness_ratio": 2.5,
      "chain_start_block": 137,
      "chain_start_event_index": 31,
      "chain_start_recovery_average_debt": 3.0,
      "chain_start_recovery_distance_blocks": 1,
      "chain_start_recovery_end_block": 137,
      "chain_start_recovery_found": true,
      "chain_start_recovery_start_block": 137,
      "chain_start_recovery_surplus": 1.415037499278844,
      "hardness_score": 15.100955299032181,
      "n0": 9780657630,
      "post_chain_recovery_average_debt": 1.587719298245614,
      "post_chain_recovery_distance_blocks": 114,
      "post_chain_recovery_end_block": 257,
      "post_chain_recovery_found": true,
      "post_chain_recovery_start_block": 144,
      "post_chain_recovery_surplus": 0.00275679752445801,
      "post_chain_start_block": 144,
      "recovery_distance_gap": 113
    },
    "longest_recovery_episode": {
      "chain_average_debt": 1.4285714285714286,
      "chain_blocks": 7,
      "chain_debt": 10,
      "chain_deficit_below_threshold": 0.15639107214972747,
      "chain_end_block": 143,
      "chain_end_event_index": 31,
      "chain_length_segments": 1,
      "chain_max_cheapness_ratio": 2.5,
      "chain_start_block": 137,
      "chain_start_event_index": 31,
      "chain_start_recovery_average_debt": 3.0,
      "chain_start_recovery_distance_blocks": 1,
      "chain_start_recovery_end_block": 137,
      "chain_start_recovery_found": true,
      "chain_start_recovery_start_block": 137,
      "chain_start_recovery_surplus": 1.415037499278844,
      "hardness_score": 15.100955299032181,
      "n0": 9780657630,
      "post_chain_recovery_average_debt": 1.587719298245614,
      "post_chain_recovery_distance_blocks": 114,
      "post_chain_recovery_end_block": 257,
      "post_chain_recovery_found": true,
      "post_chain_recovery_start_block": 144,
      "post_chain_recovery_surplus": 0.00275679752445801,
      "post_chain_start_block": 144,
      "recovery_distance_gap": 113
    },
    "max_hardness_score": 15.100955299032181,
    "max_post_chain_recovery_distance": 114,
    "min_post_chain_recovery_surplus": 0.00275679752445801,
    "n0": 9780657630,
    "odd_blocks": 425,
    "odd_start": 4890328815,
    "post_chain_recovered": 18,
    "post_chain_unrecovered": 0,
    "reaches_1": true,
    "tightest_surplus_episode": {
      "chain_average_debt": 1.4285714285714286,
      "chain_blocks": 7,
      "chain_debt": 10,
      "chain_deficit_below_threshold": 0.15639107214972747,
      "chain_end_block": 143,
      "chain_end_event_index": 31,
      "chain_length_segments": 1,
      "chain_max_cheapness_ratio": 2.5,
      "chain_start_block": 137,
      "chain_start_event_index": 31,
      "chain_start_recovery_average_debt": 3.0,
      "chain_start_recovery_distance_blocks": 1,
      "chain_start_recovery_end_block": 137,
      "chain_start_recovery_found": true,
      "chain_start_recovery_start_block": 137,
      "chain_start_recovery_surplus": 1.415037499278844,
      "hardness_score": 15.100955299032181,
      "n0": 9780657630,
      "post_chain_recovery_average_debt": 1.587719298245614,
      "post_chain_recovery_distance_blocks": 114,
      "post_chain_recovery_end_block": 257,
      "post_chain_recovery_found": true,
      "post_chain_recovery_start_block": 144,
      "post_chain_recovery_surplus": 0.00275679752445801,
      "post_chain_start_block": 144,
      "recovery_distance_gap": 113
    },
    "trajectory_average_debt": 1.6611764705882353,
    "trajectory_total_debt": 706
  },
  "current_longest_recovery": {
    "candidate_index": 191,
    "chain_episodes": 18,
    "hardest_episode": {
      "chain_average_debt": 1.4285714285714286,
      "chain_blocks": 7,
      "chain_debt": 10,
      "chain_deficit_below_threshold": 0.15639107214972747,
      "chain_end_block": 143,
      "chain_end_event_index": 31,
      "chain_length_segments": 1,
      "chain_max_cheapness_ratio": 2.5,
      "chain_start_block": 137,
      "chain_start_event_index": 31,
      "chain_start_recovery_average_debt": 3.0,
      "chain_start_recovery_distance_blocks": 1,
      "chain_start_recovery_end_block": 137,
      "chain_start_recovery_found": true,
      "chain_start_recovery_start_block": 137,
      "chain_start_recovery_surplus": 1.415037499278844,
      "hardness_score": 15.100955299032181,
      "n0": 9780657630,
      "post_chain_recovery_average_debt": 1.587719298245614,
      "post_chain_recovery_distance_blocks": 114,
      "post_chain_recovery_end_block": 257,
      "post_chain_recovery_found": true,
      "post_chain_recovery_start_block": 144,
      "post_chain_recovery_surplus": 0.00275679752445801,
      "post_chain_start_block": 144,
      "recovery_distance_gap": 113
    },
    "longest_recovery_episode": {
      "chain_average_debt": 1.4285714285714286,
      "chain_blocks": 7,
      "chain_debt": 10,
      "chain_deficit_below_threshold": 0.15639107214972747,
      "chain_end_block": 143,
      "chain_end_event_index": 31,
      "chain_length_segments": 1,
      "chain_max_cheapness_ratio": 2.5,
      "chain_start_block": 137,
      "chain_start_event_index": 31,
      "chain_start_recovery_average_debt": 3.0,
      "chain_start_recovery_distance_blocks": 1,
      "chain_start_recovery_end_block": 137,
      "chain_start_recovery_found": true,
      "chain_start_recovery_start_block": 137,
      "chain_start_recovery_surplus": 1.415037499278844,
      "hardness_score": 15.100955299032181,
      "n0": 9780657630,
      "post_chain_recovery_average_debt": 1.587719298245614,
      "post_chain_recovery_distance_blocks": 114,
      "post_chain_recovery_end_block": 257,
      "post_chain_recovery_found": true,
      "post_chain_recovery_start_block": 144,
      "post_chain_recovery_surplus": 0.00275679752445801,
      "post_chain_start_block": 144,
      "recovery_distance_gap": 113
    },
    "max_hardness_score": 15.100955299032181,
    "max_post_chain_recovery_distance": 114,
    "min_post_chain_recovery_surplus": 0.00275679752445801,
    "n0": 9780657630,
    "odd_blocks": 425,
    "odd_start": 4890328815,
    "post_chain_recovered": 18,
    "post_chain_unrecovered": 0,
    "reaches_1": true,
    "tightest_surplus_episode": {
      "chain_average_debt": 1.4285714285714286,
      "chain_blocks": 7,
      "chain_debt": 10,
      "chain_deficit_below_threshold": 0.15639107214972747,
      "chain_end_block": 143,
      "chain_end_event_index": 31,
      "chain_length_segments": 1,
      "chain_max_cheapness_ratio": 2.5,
      "chain_start_block": 137,
      "chain_start_event_index": 31,
      "chain_start_recovery_average_debt": 3.0,
      "chain_start_recovery_distance_blocks": 1,
      "chain_start_recovery_end_block": 137,
      "chain_start_recovery_found": true,
      "chain_start_recovery_start_block": 137,
      "chain_start_recovery_surplus": 1.415037499278844,
      "hardness_score": 15.100955299032181,
      "n0": 9780657630,
      "post_chain_recovery_average_debt": 1.587719298245614,
      "post_chain_recovery_distance_blocks": 114,
      "post_chain_recovery_end_block": 257,
      "post_chain_recovery_found": true,
      "post_chain_recovery_start_block": 144,
      "post_chain_recovery_surplus": 0.00275679752445801,
      "post_chain_start_block": 144,
      "recovery_distance_gap": 113
    },
    "trajectory_average_debt": 1.6611764705882353,
    "trajectory_total_debt": 706
  },
  "current_tightest_surplus": {
    "candidate_index": 191,
    "chain_episodes": 18,
    "hardest_episode": {
      "chain_average_debt": 1.4285714285714286,
      "chain_blocks": 7,
      "chain_debt": 10,
      "chain_deficit_below_threshold": 0.15639107214972747,
      "chain_end_block": 143,
      "chain_end_event_index": 31,
      "chain_length_segments": 1,
      "chain_max_cheapness_ratio": 2.5,
      "chain_start_block": 137,
      "chain_start_event_index": 31,
      "chain_start_recovery_average_debt": 3.0,
      "chain_start_recovery_distance_blocks": 1,
      "chain_start_recovery_end_block": 137,
      "chain_start_recovery_found": true,
      "chain_start_recovery_start_block": 137,
      "chain_start_recovery_surplus": 1.415037499278844,
      "hardness_score": 15.100955299032181,
      "n0": 9780657630,
      "post_chain_recovery_average_debt": 1.587719298245614,
      "post_chain_recovery_distance_blocks": 114,
      "post_chain_recovery_end_block": 257,
      "post_chain_recovery_found": true,
      "post_chain_recovery_start_block": 144,
      "post_chain_recovery_surplus": 0.00275679752445801,
      "post_chain_start_block": 144,
      "recovery_distance_gap": 113
    },
    "longest_recovery_episode": {
      "chain_average_debt": 1.4285714285714286,
      "chain_blocks": 7,
      "chain_debt": 10,
      "chain_deficit_below_threshold": 0.15639107214972747,
      "chain_end_block": 143,
      "chain_end_event_index": 31,
      "chain_length_segments": 1,
      "chain_max_cheapness_ratio": 2.5,
      "chain_start_block": 137,
      "chain_start_event_index": 31,
      "chain_start_recovery_average_debt": 3.0,
      "chain_start_recovery_distance_blocks": 1,
      "chain_start_recovery_end_block": 137,
      "chain_start_recovery_found": true,
      "chain_start_recovery_start_block": 137,
      "chain_start_recovery_surplus": 1.415037499278844,
      "hardness_score": 15.100955299032181,
      "n0": 9780657630,
      "post_chain_recovery_average_debt": 1.587719298245614,
      "post_chain_recovery_distance_blocks": 114,
      "post_chain_recovery_end_block": 257,
      "post_chain_recovery_found": true,
      "post_chain_recovery_start_block": 144,
      "post_chain_recovery_surplus": 0.00275679752445801,
      "post_chain_start_block": 144,
      "recovery_distance_gap": 113
    },
    "max_hardness_score": 15.100955299032181,
    "max_post_chain_recovery_distance": 114,
    "min_post_chain_recovery_surplus": 0.00275679752445801,
    "n0": 9780657630,
    "odd_blocks": 425,
    "odd_start": 4890328815,
    "post_chain_recovered": 18,
    "post_chain_unrecovered": 0,
    "reaches_1": true,
    "tightest_surplus_episode": {
      "chain_average_debt": 1.4285714285714286,
      "chain_blocks": 7,
      "chain_debt": 10,
      "chain_deficit_below_threshold": 0.15639107214972747,
      "chain_end_block": 143,
      "chain_end_event_index": 31,
      "chain_length_segments": 1,
      "chain_max_cheapness_ratio": 2.5,
      "chain_start_block": 137,
      "chain_start_event_index": 31,
      "chain_start_recovery_average_debt": 3.0,
      "chain_start_recovery_distance_blocks": 1,
      "chain_start_recovery_end_block": 137,
      "chain_start_recovery_found": true,
      "chain_start_recovery_start_block": 137,
      "chain_start_recovery_surplus": 1.415037499278844,
      "hardness_score": 15.100955299032181,
      "n0": 9780657630,
      "post_chain_recovery_average_debt": 1.587719298245614,
      "post_chain_recovery_distance_blocks": 114,
      "post_chain_recovery_end_block": 257,
      "post_chain_recovery_found": true,
      "post_chain_recovery_start_block": 144,
      "post_chain_recovery_surplus": 0.00275679752445801,
      "post_chain_start_block": 144,
      "recovery_distance_gap": 113
    },
    "trajectory_average_debt": 1.6611764705882353,
    "trajectory_total_debt": 706
  },
  "frontier_stable": true,
  "harder_than_previous_critical": false,
  "hardness_delta_vs_previous": 0.0,
  "previous_critical_distance": 114,
  "previous_critical_hardness": 15.100955299032181,
  "previous_critical_min_surplus": 0.00275679752445801,
  "previous_critical_n0": 9780657630,
  "previous_critical_surplus": 0.002757,
  "same_case": true,
  "version": "v1.2"
}
